[{"Time":"1658188800","Temperature":66.87,"Humidity":80.51,"Battery level":"low","Rain":0.07,"Wind":9.5},{"Time":"1658192400","Temperature":63.52,"Humidity":38.48,"Battery level":"full","Rain":0.33,"Wind":8.85},{"Time":"1658196000","Temperature":27.81,"Humidity":46.51,"Battery level":"high","Rain":0.93,"Wind":15.93},{"Time":"1658199600","Temperature":25.48,"Humidity":99.45,"Battery level":"high","Rain":0.49,"Wind":9.26},{"Time":"1658203200","Temperature":33.3,"Humidity":53.36,"Battery level":"full","Rain":1.07,"Wind":16.05},{"Time":"1658206800","Temperature":27.14,"Humidity":27.18,"Battery level":"full","Rain":0.63,"Wind":13.01},{"Time":"1658210400","Temperature":14.61,"Humidity":51.92,"Battery level":"high","Rain":0.48,"Wind":7.99},{"Time":"1658214000","Temperature":59.49,"Humidity":93.89,"Battery level":"medium","Rain":0.57,"Wind":16.7},{"Time":"1658217600","Temperature":24.49,"Humidity":15.16,"Battery level":"medium","Rain":0.37,"Wind":5.22},{"Time":"1658221200","Temperature":11.7,"Humidity":42.51,"Battery level":"full","Rain":0.9,"Wind":15.08},{"Time":"1658224800","Temperature":51.69,"Humidity":61.11,"Battery level":"full","Rain":0.31,"Wind":11.25},{"Time":"1658228400","Temperature":63,"Humidity":63.99,"Battery level":"full","Rain":0.35,"Wind":5.61},{"Time":"1658232000","Temperature":1.11,"Humidity":47.81,"Battery level":"medium","Rain":0.5,"Wind":3.9},{"Time":"1658235600","Temperature":20.86,"Humidity":88.29,"Battery level":"medium","Rain":0.5,"Wind":10.22},{"Time":"1658239200","Temperature":26.47,"Humidity":59.54,"Battery level":"high","Rain":0.13,"Wind":2.23},{"Time":"1658242800","Temperature":28.09,"Humidity":63.04,"Battery level":"low","Rain":1.04,"Wind":15.64},{"Time":"1658246400","Temperature":67.59,"Humidity":80.76,"Battery level":"high","Rain":0.85,"Wind":15.65},{"Time":"1658250000","Temperature":3.85,"Humidity":23.12,"Battery level":"high","Rain":0.97,"Wind":3.6},{"Time":"1658253600","Temperature":56.17,"Humidity":98.39,"Battery level":"high","Rain":0.44,"Wind":10.67},{"Time":"1658257200","Temperature":49.26,"Humidity":70.77,"Battery level":"medium","Rain":0.92,"Wind":2.72},{"Time":"1658260800","Temperature":59.4,"Humidity":86.76,"Battery level":"full","Rain":1.17,"Wind":18.36},{"Time":"1658264400","Temperature":21.34,"Humidity":93.9,"Battery level":"high","Rain":0.34,"Wind":10.96},{"Time":"1658268000","Temperature":2.23,"Humidity":26.24,"Battery level":"low","Rain":0.26,"Wind":0.15},{"Time":"1658271600","Temperature":28.42,"Humidity":49.37,"Battery level":"high","Rain":0.16,"Wind":15.76}]